sloww/__init__.py
sloww/cli.py
sloww/constants.py
sloww/proxy.py
sloww-0.1.0.dist-info/LICENSE
sloww-0.1.0.dist-info/METADATA
sloww-0.1.0.dist-info/WHEEL
sloww-0.1.0.dist-info/entry_points.txt
sloww-0.1.0.dist-info/RECORD
