Metadata-Version: 2.3
Name: sloww
Version: 0.1.0
Summary: A lightweight TCP proxy that adds configurable delays and bandwidth limits
License: MIT
Author: Eric Gazoni
Author-email: eric@adimian.com
Requires-Python: >=3.11
Classifier: License :: OSI Approved :: MIT License
Classifier: Programming Language :: Python :: 3
Classifier: Programming Language :: Python :: 3.11
Classifier: Programming Language :: Python :: 3.12
Classifier: Programming Language :: Python :: 3.13
Requires-Dist: click (>=8.2.1,<9.0.0)
